assignment_manager/__init__.py
assignment_manager/assignments.py
assignment_manager/data.py
assignment_manager/io.py
assignment_manager/main.py
assignment_manager-0.1.8.dist-info/LICENSE
assignment_manager-0.1.8.dist-info/METADATA
assignment_manager-0.1.8.dist-info/WHEEL
assignment_manager-0.1.8.dist-info/entry_points.txt
assignment_manager-0.1.8.dist-info/top_level.txt
assignment_manager-0.1.8.dist-info/RECORD
